{".class":"MypyFile","_fullname":"maxminddb.types","future_import_flags":[],"is_partial_stub_package":false,"is_stub":false,"names":{".class":"SymbolTable","AnyStr":{".class":"SymbolTableNode","cross_ref":"typing.AnyStr","kind":"Gdef","module_hidden":true,"module_public":false},"Dict":{".class":"SymbolTableNode","cross_ref":"typing.Dict","kind":"Gdef","module_hidden":true,"module_public":false},"List":{".class":"SymbolTableNode","cross_ref":"typing.List","kind":"Gdef","module_hidden":true,"module_public":false},"Primitive":{".class":"SymbolTableNode","kind":"Gdef","node":{".class":"TypeAlias","alias_tvars":[{".class":"TypeVarType","default":{".class":"AnyType","missing_import_name":null,"source_any":null,"type_of_any":4},"fullname":"typing.AnyStr","id":1,"name":"AnyStr","namespace":"maxminddb.types.Primitive","upper_bound":"builtins.object","values":["builtins.str","builtins.bytes"],"variance":0}],"column":0,"fullname":"maxminddb.types.Primitive","line":9,"no_args":false,"normalized":false,"target":{".class":"UnionType","items":[{".class":"TypeVarType","default":{".class":"AnyType","missing_import_name":null,"source_any":null,"type_of_any":4},"fullname":"typing.AnyStr","id":1,"name":"AnyStr","namespace":"maxminddb.types.Primitive","upper_bound":"builtins.object","values":["builtins.str","builtins.bytes"],"variance":0},"builtins.bool","builtins.float","builtins.int"]}}},"Record":{".class":"SymbolTableNode","kind":"Gdef","node":{".class":"TypeAlias","alias_tvars":[],"column":0,"fullname":"maxminddb.types.Record","line":10,"no_args":false,"normalized":false,"target":{".class":"UnionType","items":[{".class":"TypeAliasType","args":[{".class":"AnyType","missing_import_name":null,"source_any":null,"type_of_any":4}],"type_ref":"maxminddb.types.Primitive"},"maxminddb.types.RecordList","maxminddb.types.RecordDict"]}}},"RecordDict":{".class":"SymbolTableNode","kind":"Gdef","node":{".class":"TypeInfo","_promote":[],"abstract_attributes":[],"alt_promote":null,"bases":[{".class":"Instance","args":["builtins.str",{".class":"TypeAliasType","args":[],"type_ref":"maxminddb.types.Record"}],"type_ref":"builtins.dict"}],"dataclass_transform_spec":null,"declared_metaclass":null,"defn":{".class":"ClassDef","fullname":"maxminddb.types.RecordDict","name":"RecordDict","type_vars":[]},"deletable_attributes":[],"flags":[],"fullname":"maxminddb.types.RecordDict","has_param_spec_type":false,"metaclass_type":"abc.ABCMeta","metadata":{},"module_name":"maxminddb.types","mro":["maxminddb.types.RecordDict","builtins.dict","typing.MutableMapping","typing.Mapping","typing.Collection","typing.Iterable","typing.Container","builtins.object"],"names":{".class":"SymbolTable"},"self_type":null,"slots":null,"tuple_type":null,"type_vars":[],"typeddict_type":null}},"RecordList":{".class":"SymbolTableNode","kind":"Gdef","node":{".class":"TypeInfo","_promote":[],"abstract_attributes":[],"alt_promote":null,"bases":[{".class":"Instance","args":[{".class":"TypeAliasType","args":[],"type_ref":"maxminddb.types.Record"}],"type_ref":"builtins.list"}],"dataclass_transform_spec":null,"declared_metaclass":null,"defn":{".class":"ClassDef","fullname":"maxminddb.types.RecordList","name":"RecordList","type_vars":[]},"deletable_attributes":[],"flags":[],"fullname":"maxminddb.types.RecordList","has_param_spec_type":false,"metaclass_type":"abc.ABCMeta","metadata":{},"module_name":"maxminddb.types","mro":["maxminddb.types.RecordList","builtins.list","typing.MutableSequence","typing.Sequence","typing.Collection","typing.Reversible","typing.Iterable","typing.Container","builtins.object"],"names":{".class":"SymbolTable"},"self_type":null,"slots":null,"tuple_type":null,"type_vars":[],"typeddict_type":null}},"Union":{".class":"SymbolTableNode","cross_ref":"typing.Union","kind":"Gdef","module_hidden":true,"module_public":false},"__annotations__":{".class":"SymbolTableNode","kind":"Gdef","node":{".class":"Var","flags":["is_ready"],"fullname":"maxminddb.types.__annotations__","name":"__annotations__","type":{".class":"Instance","args":["builtins.str",{".class":"AnyType","missing_import_name":null,"source_any":null,"type_of_any":6}],"type_ref":"builtins.dict"}}},"__doc__":{".class":"SymbolTableNode","kind":"Gdef","node":{".class":"Var","flags":["is_ready"],"fullname":"maxminddb.types.__doc__","name":"__doc__","type":"builtins.str"}},"__file__":{".class":"SymbolTableNode","kind":"Gdef","node":{".class":"Var","flags":["is_ready"],"fullname":"maxminddb.types.__file__","name":"__file__","type":"builtins.str"}},"__name__":{".class":"SymbolTableNode","kind":"Gdef","node":{".class":"Var","flags":["is_ready"],"fullname":"maxminddb.types.__name__","name":"__name__","type":"builtins.str"}},"__package__":{".class":"SymbolTableNode","kind":"Gdef","node":{".class":"Var","flags":["is_ready"],"fullname":"maxminddb.types.__package__","name":"__package__","type":"builtins.str"}}},"path":"/home/runner/work/sentry/sentry/.venv/lib/python3.8/site-packages/maxminddb/types.py"}
